solace_agent_mesh/__init__.py
solace_agent_mesh/agent/__init__.py
solace_agent_mesh/agent/adk/__init__.py
solace_agent_mesh/agent/adk/alembic.ini
solace_agent_mesh/agent/adk/app_llm_agent.py
solace_agent_mesh/agent/adk/callbacks.py
solace_agent_mesh/agent/adk/embed_resolving_mcp_toolset.py
solace_agent_mesh/agent/adk/intelligent_mcp_callbacks.py
solace_agent_mesh/agent/adk/mcp_content_processor.py
solace_agent_mesh/agent/adk/runner.py
solace_agent_mesh/agent/adk/schema_migration.py
solace_agent_mesh/agent/adk/services.py
solace_agent_mesh/agent/adk/setup.py
solace_agent_mesh/agent/adk/stream_parser.py
solace_agent_mesh/agent/adk/tool_wrapper.py
solace_agent_mesh/agent/adk/alembic/README
solace_agent_mesh/agent/adk/alembic/env.py
solace_agent_mesh/agent/adk/alembic/script.py.mako
solace_agent_mesh/agent/adk/alembic/versions/e2902798564d_adk_session_db_upgrade.py
solace_agent_mesh/agent/adk/artifacts/__init__.py
solace_agent_mesh/agent/adk/artifacts/filesystem_artifact_service.py
solace_agent_mesh/agent/adk/artifacts/s3_artifact_service.py
solace_agent_mesh/agent/adk/models/lite_llm.py
solace_agent_mesh/agent/adk/models/oauth2_token_manager.py
solace_agent_mesh/agent/protocol/__init__.py
solace_agent_mesh/agent/protocol/event_handlers.py
solace_agent_mesh/agent/proxies/__init__.py
solace_agent_mesh/agent/proxies/a2a/__init__.py
solace_agent_mesh/agent/proxies/a2a/app.py
solace_agent_mesh/agent/proxies/a2a/component.py
solace_agent_mesh/agent/proxies/a2a/config.py
solace_agent_mesh/agent/proxies/a2a/oauth_token_cache.py
solace_agent_mesh/agent/proxies/base/__init__.py
solace_agent_mesh/agent/proxies/base/app.py
solace_agent_mesh/agent/proxies/base/component.py
solace_agent_mesh/agent/proxies/base/config.py
solace_agent_mesh/agent/proxies/base/proxy_task_context.py
solace_agent_mesh/agent/sac/__init__.py
solace_agent_mesh/agent/sac/app.py
solace_agent_mesh/agent/sac/component.py
solace_agent_mesh/agent/sac/patch_adk.py
solace_agent_mesh-1.14.0.dist-info/METADATA
solace_agent_mesh-1.14.0.dist-info/WHEEL
solace_agent_mesh-1.14.0.dist-info/entry_points.txt
solace_agent_mesh-1.14.0.dist-info/licenses/LICENSE
solace_agent_mesh-1.14.0.dist-info/RECORD
