Metadata-Version: 2.4
Name: solace-agent-mesh
Version: 1.14.0
Summary: Solace Agent Mesh is an open-source framework for building event-driven, multi-agent AI systems where specialized agents collaborate on complex tasks.
Project-URL: Homepage, https://github.com/SolaceLabs/solace-agent-mesh
Project-URL: Repository, https://github.com/SolaceLabs/solace-agent-mesh
Author-email: SolaceLabs <solacelabs@solace.com>
License:                                  Apache License
License-File: LICENSE
Classifier: License :: OSI Approved :: Apache Software License
Classifier: Operating System :: OS Independent
Classifier: Programming Language :: Python :: 3
Classifier: Programming Language :: Python :: 3.11
Classifier: Programming Language :: Python :: 3.13
Classifier: Topic :: Software Development :: Libraries :: Application Frameworks
Requires-Python: >=3.10.16
Requires-Dist: a2a-sdk[http-server]==0.3.7
Requires-Dist: alembic==1.16.5
Requires-Dist: asteval==1.0.6
Requires-Dist: authlib==1.6.5
Requires-Dist: azure-cognitiveservices-speech==1.41.1
Requires-Dist: beautifulsoup4==4.13.5
Requires-Dist: boto3==1.40.37
Requires-Dist: click==8.1.8
Requires-Dist: fastapi==0.120.1
Requires-Dist: flask-cors==6.0.1
Requires-Dist: flask==3.0.3
Requires-Dist: gitpython==3.1.45
Requires-Dist: google-adk==1.18.0
Requires-Dist: google-genai==1.49.0
Requires-Dist: holidays==0.81.0
Requires-Dist: httpx==0.28.1
Requires-Dist: itsdangerous==2.2.0
Requires-Dist: jmespath==1.0.1
Requires-Dist: jsonpath-ng==1.7.0
Requires-Dist: jwcrypto==1.5.6
Requires-Dist: kaleido==0.2.1
Requires-Dist: litellm==1.76.3
Requires-Dist: markdownify==1.2.0
Requires-Dist: markitdown[all]==0.1.4
Requires-Dist: mermaid-cli==0.1.2
Requires-Dist: numpy==2.2.6
Requires-Dist: openai==1.99.9
Requires-Dist: pandas==2.3.2
Requires-Dist: playwright==1.55.0
Requires-Dist: plotly==6.3.0
Requires-Dist: psycopg2-binary==2.9.10
Requires-Dist: pydantic==2.11.9
Requires-Dist: pydub==0.25.1
Requires-Dist: pystache==0.6.8
Requires-Dist: python-dotenv==1.1.1
Requires-Dist: python-jwt==4.1.0
Requires-Dist: python-liquid==2.1.0
Requires-Dist: python-multipart==0.0.20
Requires-Dist: pyyaml==6.0.2
Requires-Dist: rich==13.9.4
Requires-Dist: rouge==1.0.1
Requires-Dist: solace-ai-connector==3.3.0
Requires-Dist: sqlalchemy==2.0.40
Requires-Dist: sse-starlette==3.0.2
Requires-Dist: starlette==0.49.1
Requires-Dist: toml==0.10.2
Requires-Dist: uvicorn[standard]==0.37.0
Provides-Extra: employee-tools
Requires-Dist: holidays==0.81.0; extra == 'employee-tools'
Provides-Extra: gcs
Requires-Dist: google-cloud-storage==3.5.0; extra == 'gcs'
Provides-Extra: test
Requires-Dist: aiosqlite; extra == 'test'
Requires-Dist: asyncpg; extra == 'test'
Requires-Dist: fastmcp==2.11.2; extra == 'test'
Requires-Dist: httpx>=0.25; extra == 'test'
Requires-Dist: psycopg2-binary; extra == 'test'
Requires-Dist: pytest-asyncio; extra == 'test'
Requires-Dist: pytest-cov>=4.0.0; extra == 'test'
Requires-Dist: pytest-httpx>=0.35.0; extra == 'test'
Requires-Dist: pytest-mock>=3.0.0; extra == 'test'
Requires-Dist: pytest-xdist>=3.5.0; extra == 'test'
Requires-Dist: pytest>=8.0.0; extra == 'test'
Requires-Dist: respx; extra == 'test'
Requires-Dist: ruff; extra == 'test'
Requires-Dist: testcontainers; extra == 'test'
Provides-Extra: vertex
Requires-Dist: google-cloud-aiplatform==1.126.1; extra == 'vertex'
